{
  "kind": "court",
  "slug": "family-court-lawyer-lahore",
  "route": "/courts/family-court-lawyer-lahore",
  "parent": {
    "label": "Lahore Courts",
    "slug": "courts",
    "route": "/courts"
  },
  "ancestors": [
    {
      "label": "Lahore Courts",
      "slug": "courts",
      "route": "/courts"
    }
  ],
  "seo": {
    "title": "Family Court Lawyer Lahore | Divorce, Khula, Custody",
    "description": "Expert family court representation in Lahore: divorce, khula, custody, maintenance, dower recovery. 50 years specialist practice in Aiwan-e-Adal.",
    "canonicalPath": "/courts/family-court-lawyer-lahore"
  },
  "hero": {
    "eyebrow": "Lahore Family Courts",
    "h1": "Family Court Lawyer in Lahore",
    "intro": "Specialist family court lawyer in Lahore. We handle divorce, khula, child custody, maintenance, dower, and dowry recovery at Aiwan-e-Adal Family Courts. 50 years of experience."
  },
  "bodyMarkdown": "Reviewed by Bilal Saeed, Advocate (Punjab Bar Council). Last updated May 2026.\n\nFamily court disputes touch the most sensitive areas of life: dissolution of marriage, custody of children, maintenance of wife and dependants, dower and dowry recovery. Expert representation with courtroom experience and statutory knowledge helps you navigate complexity with clarity and care. Saeed Law Firm has specialised in family law since 1975, handling over 800 matters across all categories at Lahore's Aiwan-e-Adal Family Courts and the Lahore High Court.\n\nThis guide explains what the Family Courts in Lahore handle, how they work, and what you should expect if you need to file suit or defend one.\n\n## What Are the Lahore Family Courts?\n\nThe Family Courts exist to resolve disputes under unified legal authority. Established under West Pakistan law, they exercise exclusive jurisdiction over matters listed in the Schedule. If your case involves dissolution of marriage, custody, or maintenance, this is the proper forum.\n\nThe court complex at Aiwan-e-Adal, Mall Road comprises three benches:\n\n- Senior Civil Judges (Family): hear appeals and complex original cases\n- Civil Judges (Family): hear most original family suits\n- Guardian Court: handles custody and guardianship petitions under the Guardians and Wards Act 1890\n\nAll apply West Pakistan law, MFLO 1961, the Dissolution of Muslim Marriages Act 1939, the Guardians and Wards Act 1890, and the Dowry Act 1976. A specialist practice knows how each statute operates in practice.\n\n## What Matters Do These Courts Decide?\n\nJurisdiction is set out in the Schedule to the West Pakistan Family Courts Act 1964. Our representation works within this defined scope. Whether your matter is [dissolution of marriage](/divorce-lawyer-in-lahore), [khula](/khula-lawyer-in-lahore), [custody](/child-custody-lawyer-in-lahore), or maintenance, understanding the scope helps you prepare. Here is what the courts decide:\n\n| Matter Type | What the Court Decides | What to Expect |\n|---|---|---|\n| Dissolution of marriage | Talaq validity, khula petitions, grounds under law | Decree nisi, then decree absolute after final hearing |\n| Maintenance (nafaqa) | Wife's maintenance during and after marriage; children's maintenance | Monthly sum fixed; commencement date set; arrears recoverable |\n| Dower (haq mehr) | Mahr owed to wife; haq mehr recovery and enforcement | Decree for payment; execution warrant if unpaid |\n| Dowry articles | Personal property brought to marriage; recovery under Dowry Act 1976 | Articles returned or damages awarded; dowry register is evidence |\n| Custody (hizanat) | Care, control, and custody of minor children | Guardianship awarded based on welfare of child; visitation set |\n| Guardianship | Guardianship of minors under Guardians and Wards Act | Guardian appointed; property managed; conditions set |\n| Restitution of conjugal rights | Husband's right to wife's society and cohabitation | Decree for restitution issued; breach may ground talaq |\n| Jactitation of marriage | False claim of marriage to claimant | Declaration that no valid marriage exists |\n\nMatters outside this Schedule (inheritance, succession, property) go to Civil Courts. A specialist quickly identifies the correct forum, avoiding procedural delays. If you need representation in Lahore courts, our [experienced lawyers](/lawyers-in-lahore) can advise on jurisdiction and next steps.\n\n## How Does Procedure Work: A Step-by-Step Guide?\n\nThe process from filing to decree follows a structured sequence. Understanding each stage helps you and your lawyer gather evidence at the right time and prepare for the outcome.\n\n1. Plaint drafting and filing: lawyer drafts detailed statement of claims with legal grounds (e.g. Section 7 MFLO 1961 for talaq); court fee paid under Court Fees Act 1870\n2. Service of summons: defendant receives notice; proper service is critical\n3. Mandatory reconciliation: judge or Faizan-e-Islam committee attempts settlement before merits hearing\n4. Framing of issues: once reconciliation fails, judge narrows dispute into specific legal questions\n5. Evidence: plaintiff presents witness testimony and documents (nikah nama, dowry register, income proof, school records); defendant cross-examines\n6. Defendant's case: defendant presents their evidence; plaintiff cross-examines\n7. Arguments: written and oral submissions on law and fact; case law and statute interpretation decide outcome\n8. Judgment and decree: judge delivers judgment; if suit succeeds, decree issued (dissolution decrees are nisi initially, becoming absolute after a set period)\n9. Registration and execution: dissolution decrees registered with NADRA; maintenance, dower, and dowry decrees executed through warrant of arrest, garnishment, or asset attachment if unpaid\n\nRealistic timelines: uncontested khula or talaq takes 6 to 9 months; contested divorce or custody takes 9 to 18 months; child custody alone takes 4 to 12 months; appeals to District Court add 6 to 12 months. Adjournments and judge efficiency drive the actual pace. A specialist minimises unnecessary delays.\n\n## Key Questions: Reconciliation, Forum, and Absent Defendants?\n\n**Is reconciliation really mandatory?** Yes. Section 5 of the West Pakistan Family Courts Act 1964 makes reconciliation a compulsory first step. Even if both husband and wife agree to divorce before filing suit, the court will not skip this stage. In Islamic law (fiqh), reconciliation is a principle: God prefers reconciliation. The law reflects this principle. However, if reconciliation is genuinely impossible (abuse is documented, or parties have not spoken in years), the judge may abbreviate the process.\n\n**What is the difference between Family Court and Guardian Court?** Both courts sit in the same Aiwan-e-Adal complex, but they have different statutory bases. The Guardian Court hears custody and guardianship under the Guardians and Wards Act 1890. The Family Court hears custody as part of a divorce or family dispute case. If a custody petition is already pending in Guardian Court, a new petition cannot be filed in Family Court. Forum choice matters: it determines which judge hears your case and what law applies. For court marriage matters, see our [court marriage lawyer guide](/court-marriage-lawyer-in-lahore).\n\n**What if the defendant doesn't appear?** The case proceeds ex-parte (in the defendant's absence). The judge hears your evidence and your lawyer's arguments without the defendant's response. You can still win, especially in talaq or maintenance cases where your evidence is strong. However, ex-parte decrees are vulnerable to appeal. Service becomes critical: your lawyer ensures proper service and obtains proof (service return) to defeat any later challenge. Personal appearance by the defendant, though sometimes emotionally difficult, strengthens the finality of the decree.\n\n## How to Work with Our Practice?\n\nWith 50 years of practice, we know the judges, institutional culture, and the precedents. We bring that experience through a structured approach:\n\n- Listening without judgment to understand your story, the emotional context, and the legal issues\n- Drafting pleadings with legal precision and factual completeness; vague pleadings lead to lost cases\n- Assembling documents: nikah nama, CNIC copies, income proof, school records, medical reports, witness affidavits, all organised and certified\n- Appearing at every hearing personally; your case receives principal counsel attention, not a subordinate's\n- Negotiating during reconciliation stage if settlement is in your interest; preparing for contest if not\n- Preparing you for cross-examination and briefing witnesses beforehand; poor witness testimony loses cases\n- Pursuing decree execution through writs of attachment, garnishment, and arrest warrants; a decree without execution is worthless\n- Evaluating grounds for appeal to District Court and preparing appellate arguments if judgment is unfavorable\n\nThis is not transactional work. It is relationship-based practice rooted in listening, preparation, and relentless attention to detail.\n\n## What External Resources Guide These Courts?\n\nThese courts operate under national statutes and align with guidance from appellate courts. Key resources:\n\nThe Lahore High Court ([https://lhc.gov.pk](https://lhc.gov.pk)) publishes rulings on family law that bind the Family Courts below. Appeals from these decrees go to the Lahore High Court for appellate review or constitutional remedy. Punjab Laws ([https://punjablaws.gov.pk](https://punjablaws.gov.pk)) publishes the full text of statutes, rules, and judicial orders. Our lawyers consult these sources regularly to ensure your case is argued with reference to the latest law and appellate precedent.\n\n## What Are Your Options If You Lose at Court?\n\nIf the judgment is against you, the District Court Lahore hears appeals. An Additional District Judge reviews the judgment de novo (as if hearing the case for the first time). If the District Court upholds the judgment, constitutional remedies may be available at the Lahore High Court: letters patent appeals (for pure legal issues) or constitutional petitions under Article 199. These are rare and reserved for serious judicial error. Appeals add 6 to 12 months to your timeline. We advise whether an appeal is worth pursuing on a cost-benefit basis or whether accepting the judgment and moving forward is wiser.\n\n## Why Choose Us?\n\nWe are a specialist practice with 50 years of accumulated experience:\n\n- 50 years of practice: since 1975, specialising in these matters. We know how judges think and what arguments succeed.\n- Over 800 matters handled: we bring experience of unusual issues, precedents we have relied on, and judicial preferences we have learned through repeated practice.\n- Principal counsel at every hearing: Bilal Saeed, our principal, is an Advocate of the Punjab Bar Council. He reviews every case personally. You work with the principal, not a junior.\n- Office near the court: we are in DHA Phase 3, a short drive from the family courts. We attend hearings without delay and respond to urgent matters the same day.\n- Confidentiality and sensitivity: disputes are private. We maintain strict confidentiality. Female staff are available for sensitive consultations. Need a [family lawyer](/family-lawyer-in-lahore) for matters beyond Family Court jurisdiction? We also handle civil disputes, labour matters, and constitutional law at the Lahore High Court.\n\n## Frequently Asked Questions About These Courts?\n\n**Where exactly is the court complex?** Aiwan-e-Adal, Mall Road, Lahore. The complex houses the Senior Civil Judges (Family), Civil Judges (Family), and Guardian Court. It is near the Mall and accessible by public transport. Our office is in DHA Phase 3, a short drive away.\n\n**How long does khula take?** Uncontested khula under the Dissolution of Muslim Marriages Act 1939 typically takes 6 to 9 months. The reconciliation stage is quick if there is no contest. Once the judge is satisfied that the woman's grounds are valid and she is consenting, the decree is issued.\n\n**Can I consult before filing suit?** Yes. We offer initial consultations to advise on your case, applicable law, realistic timelines, and costs. We listen without judgment and tell you what we can do. No obligation follows consultation.\n\n**Do you represent overseas Pakistanis?** Yes. We represent overseas Pakistanis in family cases in Lahore. Remote consultations via Zoom and WhatsApp are available. Court appearances are made by us in person.\n\n**What does legal representation cost?** Fees vary by case type and complexity. Uncontested khula or talaq suits are usually fixed-fee. Contested cases are charged stage-by-stage: pleading, evidence, and argument. We provide a written fee estimate after the initial consultation. No hidden costs.\n\n**How do I book a consultation?** Contact us via the form on this site, call +92-319-4959420, or WhatsApp the same number. We respond within one business day and schedule a consultation at your convenience. Consultations can be in-person at our Lahore office or remote.",
  "details": [
    {
      "label": "Court Address",
      "values": [
        "Family Courts at Aiwan-e-Adal, Mall Road, Lahore"
      ]
    },
    {
      "label": "Jurisdiction",
      "values": [
        "Lahore district. Exclusive jurisdiction over matters listed in Schedule, West Pakistan Family Courts Act 1964."
      ]
    },
    {
      "label": "Governing Statute",
      "values": [
        "West Pakistan Family Courts Act 1964",
        "Muslim Family Laws Ordinance 1961",
        "Dissolution of Muslim Marriages Act 1939",
        "Guardians and Wards Act 1890",
        "Dowry and Bridal Gifts (Restriction) Act 1976"
      ]
    },
    {
      "label": "Case Types We Handle",
      "values": [
        "Dissolution of marriage (talaq, khula)",
        "Dower and dowry recovery",
        "Maintenance for wife and children",
        "Custody of minors and hizanat",
        "Restitution of conjugal rights",
        "Guardianship of minors and property",
        "Jactitation of marriage"
      ]
    },
    {
      "label": "Filing Procedure",
      "values": [
        "Prepare plaint with verified statement of facts",
        "Pay court fee under Court Fees Act 1870",
        "File with Vakalatnama (power of attorney) if using our services",
        "Serve summons on defendant",
        "Attend mandatory reconciliation hearing",
        "Frame issues and proceed to evidence and argument"
      ]
    }
  ],
  "faqs": [
    {
      "q": "How do I book a consultation with Saeed Law Firm?",
      "a": "Contact us via the form on this website, call +92-319-4959420, or WhatsApp the same number. We respond within one business day and can arrange a consultation at our Lahore office or via Zoom/WhatsApp within the week. Your initial consultation is normally PKR 8,000, free for a limited time."
    },
    {
      "q": "Do you serve clients outside Lahore or overseas?",
      "a": "Yes. We represent clients across Pakistan and overseas Pakistanis. Our primary court appearances are in Lahore. Remote consultations are available via Zoom and WhatsApp, and we can coordinate with local counsel if your case involves courts elsewhere."
    },
    {
      "q": "What is your experience level in family law?",
      "a": "Saeed Law Firm has specialised in family law since 1975: 50 years of practice. We have handled over 800 matters across all categories: dissolution, custody, maintenance, dower, and dowry. Our principal, Bilal Saeed, is an Advocate enrolled with the Punjab Bar Council."
    },
    {
      "q": "How much does a family court case cost?",
      "a": "Costs depend on case type and complexity. Uncontested matters (e.g. uncontested khula or talaq) are usually fixed-fee. Contested cases are charged stage-by-stage: pleading, evidence, and argument. We provide a written fee estimate after the initial consultation."
    },
    {
      "q": "What is the realistic timeline for my case?",
      "a": "Uncontested khula or talaq decree: 6 to 9 months. Contested divorce or maintenance: 9 to 18 months. Child custody: 4 to 12 months. Timelines depend on adjournments and judicial efficiency. Appeals to District Court add 6 to 12 months."
    },
    {
      "q": "Can I consult with you before deciding to file suit?",
      "a": "Yes. We offer pre-litigation consultations. We listen to your situation, explain the relevant law, outline realistic outcomes, discuss costs, and advise whether filing suit is the right step. Many matters are best resolved by negotiation or ADR before court involvement."
    }
  ],
  "relatedPages": [
    {
      "title": "Divorce Lawyer in Lahore",
      "href": "/divorce-lawyer-in-lahore",
      "description": "Experienced divorce lawyer in Lahore handling contested and uncontested divorce, talaq, and khula at Lahore Family Courts. 50 years' specialist practice."
    },
    {
      "title": "Khula Lawyer in Lahore",
      "href": "/khula-lawyer-in-lahore",
      "description": "Khula lawyer in Lahore filing and defending khula petitions under the Dissolution of Muslim Marriages Act 1939. Confidential representation at Lahore Family Courts."
    },
    {
      "title": "Child Custody Lawyer in Lahore",
      "href": "/child-custody-lawyer-in-lahore",
      "description": "Child custody lawyer in Lahore handling hizanat petitions and guardianship proceedings at Lahore Guardian Court. Focus on welfare of the child."
    }
  ],
  "content": {
    "h1": "Family Court Lawyer in Lahore",
    "subheading": "Lahore Family Courts",
    "description": "Expert family court representation in Lahore for divorce, khula, custody, maintenance, dower and dowry recovery. Over 50 years of specialist practice.",
    "introBlocks": [
      {
        "type": "paragraph",
        "text": "Reviewed by Bilal Saeed, Advocate (Punjab Bar Council). Last updated May 2026."
      },
      {
        "type": "paragraph",
        "text": "Family court disputes touch the most sensitive areas of life: dissolution of marriage, custody of children, maintenance of wife and dependants, dower and dowry recovery. A family court lawyer in Lahore with courtroom experience helps you navigate complexity with clarity and care. Saeed Law Firm specialises in this practice area since 1975, handling over 800 matters across all categories at Lahore's Aiwan-e-Adal courts and the Lahore High Court. This guide explains what these courts handle, how they work, and what you should expect if you need to file suit or defend one."
      }
    ],
    "sections": [
      {
        "heading": "What Are the Lahore Family Courts?",
        "subheading": "Jurisdiction, Composition, and Legal Framework",
        "description": "The Family Courts exist to resolve disputes under unified legal authority. Established under West Pakistan law, they exercise exclusive jurisdiction over matters listed in the Schedule.",
        "blocks": [
          {
            "type": "paragraph",
            "text": "If your case involves dissolution of marriage, custody, or maintenance, this is the proper forum. The Family Court complex at Aiwan-e-Adal, Mall Road comprises three benches. Senior Civil Judges (Family) hear appeals and complex original cases. Civil Judges (Family) hear most original family suits. Guardian Court, within the same complex, handles custody and guardianship petitions under the Guardians and Wards Act 1890. A specialist family court lawyer in Lahore knows how each bench operates and which forum best suits your case."
          },
          {
            "type": "list",
            "items": [
              "Senior Civil Judges (Family): hear appeals and complex original cases",
              "Civil Judges (Family): hear most original family suits",
              "Guardian Court: hears custody and guardianship petitions under Guardians and Wards Act 1890",
              "All courts apply West Pakistan Family Courts Act 1964, Muslim Family Laws Ordinance 1961, Dissolution of Muslim Marriages Act 1939, Guardians and Wards Act 1890, and Dowry and Bridal Gifts (Restriction) Act 1976"
            ]
          }
        ]
      },
      {
        "heading": "What Matters Do These Courts Decide?",
        "subheading": "Jurisdiction and Case Categories",
        "description": "The jurisdiction of the Family Court is defined by the Schedule to the West Pakistan Family Courts Act 1964. Our specialist representation works within this scope.",
        "blocks": [
          {
            "type": "paragraph",
            "text": "Jurisdiction is set out in the Schedule to the West Pakistan Family Courts Act 1964. Here is what the courts decide and what you should expect in each type of case. Whether your matter is [dissolution of marriage](/divorce-lawyer-in-lahore), [khula](/khula-lawyer-in-lahore), [custody](/child-custody-lawyer-in-lahore), or maintenance, understanding the scope helps you prepare:"
          },
          {
            "type": "table",
            "headers": [
              "Matter Type",
              "What the Court Decides",
              "What to Expect"
            ],
            "rows": [
              [
                "Dissolution of marriage",
                "Talaq validity, khula petitions, grounds under law",
                "Decree nisi, then decree absolute after final hearing"
              ],
              [
                "Maintenance (nafaqa)",
                "Wife's maintenance during and after marriage; children's maintenance",
                "Monthly sum fixed; commencement date set; arrears recoverable"
              ],
              [
                "Dower (haq mehr)",
                "Mahr owed to wife; haq mehr recovery and enforcement",
                "Decree for payment; execution warrant if unpaid"
              ],
              [
                "Dowry articles",
                "Personal property brought to marriage; recovery under Dowry Act 1976",
                "Articles returned or damages awarded; dowry register is evidence"
              ],
              [
                "Custody (hizanat)",
                "Care, control, and custody of minor children",
                "Guardianship awarded based on welfare of child; visitation set"
              ],
              [
                "Guardianship",
                "Guardianship of minors under Guardians and Wards Act",
                "Guardian appointed; property managed; conditions set"
              ],
              [
                "Restitution of conjugal rights",
                "Husband's right to wife's society and cohabitation",
                "Decree for restitution issued; breach may ground talaq"
              ],
              [
                "Jactitation of marriage",
                "False claim of marriage to claimant",
                "Declaration that no valid marriage exists"
              ]
            ]
          },
          {
            "type": "paragraph",
            "text": "Matters outside this Schedule (inheritance, succession, property) go to Civil Courts. A specialist quickly identifies the correct forum, avoiding procedural delays. If you need representation in Lahore courts, our [experienced lawyers](/lawyers-in-lahore) can advise on jurisdiction and next steps."
          }
        ]
      },
      {
        "heading": "How Does Family Court Procedure Work: A Step-by-Step Guide?",
        "subheading": "Process Stages and Realistic Timelines",
        "description": "The process from filing to decree follows a structured sequence. Understanding each stage helps you and your lawyer gather evidence at the right time.",
        "blocks": [
          {
            "type": "orderedList",
            "items": [
              "Plaint drafting and filing: lawyer drafts detailed statement of claims with legal grounds (e.g. Section 7 MFLO 1961 for talaq); court fee paid under Court Fees Act 1870",
              "Service of summons: defendant receives notice; proper service is critical",
              "Mandatory reconciliation: judge or Faizan-e-Islam committee attempts settlement before merits hearing",
              "Framing of issues: once reconciliation fails, judge narrows dispute into specific legal questions",
              "Evidence: plaintiff presents witness testimony and documents (nikah nama, dowry register, income proof, school records); defendant cross-examines",
              "Defendant's case: defendant presents their evidence; plaintiff cross-examines",
              "Arguments: written and oral submissions on law and fact; case law and statute interpretation decide outcome",
              "Judgment and decree: judge delivers judgment; if suit succeeds, decree issued (dissolution decrees are nisi initially, becoming absolute after a set period)",
              "Registration and execution: dissolution decrees registered with NADRA; maintenance, dower, and dowry decrees executed through warrant of arrest, garnishment, or asset attachment if unpaid"
            ]
          },
          {
            "type": "paragraph",
            "text": "Realistic timelines: uncontested khula or talaq decree takes 6 to 9 months; contested divorce or custody takes 9 to 18 months; child custody alone takes 4 to 12 months; appeals to District Court add 6 to 12 months. Adjournments (for witnesses or fresh legal advice) and the judge's efficiency drive the actual pace. A specialist family court lawyer minimises unnecessary delays."
          }
        ]
      },
      {
        "heading": "Key Procedural Questions: Reconciliation, Forum, and Absent Defendants?",
        "subheading": "Common Concerns About Family Court Practice",
        "description": "Answers to frequent questions about reconciliation mandates, forum selection, and ex-parte proceedings.",
        "blocks": [
          {
            "type": "subheading",
            "text": "Is Reconciliation Really Mandatory?"
          },
          {
            "type": "paragraph",
            "text": "Yes. Section 5 of the West Pakistan Family Courts Act 1964 makes reconciliation a compulsory first step. Even if both husband and wife agree to divorce before filing suit, the court will not skip this stage. In Islamic law (fiqh), reconciliation is a principle: God prefers reconciliation. The law reflects this principle. However, if reconciliation is genuinely impossible (abuse is documented, or parties have not spoken in years), the judge may abbreviate the process. This is a protective rule that respects Islamic values while allowing just outcomes when relationships have truly broken down."
          },
          {
            "type": "subheading",
            "text": "What is the Difference Between Family Court and Guardian Court?"
          },
          {
            "type": "paragraph",
            "text": "Both courts sit in the same Aiwan-e-Adal complex, but they have different statutory bases. The Guardian Court hears custody and guardianship under the Guardians and Wards Act 1890. The Family Court hears custody as part of a divorce or family dispute case. If a custody petition is already pending in Guardian Court, a new petition cannot be filed in Family Court. If you are unsure which court is appropriate, your lawyer coordinates filing to avoid conflict and delay. Forum choice matters: it determines which judge hears your case and what law applies. For court marriage matters, see our [court marriage lawyer guide](/court-marriage-lawyer-in-lahore)."
          },
          {
            "type": "paragraph",
            "text": "What if the defendant doesn't appear? The case proceeds ex-parte (in the defendant's absence). The judge hears your evidence and your lawyer's arguments without the defendant's response. You can still win, especially in talaq or maintenance cases where your evidence is strong. However, ex-parte decrees are vulnerable to appeal: a defendant can later argue they did not receive proper notice. This is why service becomes critical. Your lawyer ensures proper service and obtains proof (service return) to defeat any later challenge on procedural grounds. Personal appearance by the defendant, though sometimes emotionally difficult, strengthens the finality of the decree."
          }
        ]
      },
      {
        "heading": "How to Work with a Specialist Family Court Lawyer in Lahore?",
        "subheading": "Our Approach to Family Law Practice",
        "description": "A family court lawyer in Lahore with 50 years of institutional practice knows the judges, the court's culture, and the precedents. We bring that experience to your case.",
        "blocks": [
          {
            "type": "list",
            "items": [
              "Listening without judgment to understand your story, the emotional context, and the legal issues",
              "Drafting pleadings with legal precision and factual completeness; vague pleadings lead to lost cases",
              "Assembling documents: nikah nama, CNIC copies, income proof, school records, medical reports, witness affidavits, all organised and certified",
              "Appearing at every hearing personally; your case receives principal counsel attention, not a subordinate's",
              "Negotiating during reconciliation stage if settlement is in your interest; preparing for contest if not",
              "Preparing you for cross-examination and briefing witnesses beforehand; poor witness testimony loses cases",
              "Pursuing decree execution through writs of attachment, garnishment, and arrest warrants; a decree without execution is worthless",
              "Evaluating grounds for appeal to District Court and preparing appellate arguments if judgment is unfavorable"
            ]
          },
          {
            "type": "paragraph",
            "text": "This is not transactional work. It is relationship-based practice rooted in listening, preparation, and relentless attention to detail."
          }
        ]
      },
      {
        "heading": "What External Resources Guide Lahore Family Courts?",
        "subheading": "Statutes, Case Law, and Appellate Guidance",
        "description": "These courts operate under national statutes and align with guidance from appellate courts.",
        "blocks": [
          {
            "type": "paragraph",
            "text": "The Lahore High Court ([https://lhc.gov.pk](https://lhc.gov.pk)) publishes rulings on family law that bind the Family Courts below. Appeals from these decrees go to the Lahore High Court for appellate review or constitutional remedy. Punjab Laws ([https://punjablaws.gov.pk](https://punjablaws.gov.pk)) publishes the full text of statutes, rules, and judicial orders. Our lawyers consult these sources regularly to ensure your case is argued with reference to the latest law and appellate precedent."
          }
        ]
      },
      {
        "heading": "What Are Your Options If You Lose at Family Court?",
        "subheading": "Post-Judgment Appeals and Higher Court Review",
        "description": "If the judgment is against you, the District Court hears appeals.",
        "blocks": [
          {
            "type": "paragraph",
            "text": "If the judgment is against you, the District Court Lahore hears appeals. An Additional District Judge reviews the judgment de novo (as if hearing the case for the first time). If the District Court upholds the judgment, constitutional remedies may be available at the Lahore High Court: letters patent appeals (for pure legal issues) or constitutional petitions under Article 199. These are rare and reserved for serious judicial error. Appeals add 6 to 12 months to your timeline. Your family court lawyer advises whether an appeal is worth pursuing on a cost-benefit basis or whether accepting the judgment and moving forward is the wiser course."
          }
        ]
      },
      {
        "heading": "Why Choose Our Family Law Practice in Lahore?",
        "subheading": "50 Years of Specialist Experience and Accumulated Knowledge",
        "description": "We are a specialist practice with 50 years of accumulated experience.",
        "blocks": [
          {
            "type": "list",
            "items": [
              "50 years of practice: since 1975, we have specialised in family disputes. We know how judges think and what arguments succeed.",
              "Over 800 matters handled: we bring experience of unusual issues, precedents we have relied on, and judicial preferences we have learned through repeated practice.",
              "Principal counsel at every hearing: Bilal Saeed, our principal, is an Advocate of the Punjab Bar Council. He reviews every case personally. You work with the principal, not a junior.",
              "Office near the court: we are in DHA Phase 3, a short drive from the family courts. We attend hearings without delay and respond to urgent matters the same day.",
              "Confidentiality and sensitivity: disputes are private. We maintain strict confidentiality. Female staff available for sensitive consultations."
            ]
          },
          {
            "type": "paragraph",
            "text": "Need a [family lawyer](/family-lawyer-in-lahore) for matters beyond Family Court jurisdiction? We also handle civil disputes, labour matters, and constitutional law at the Lahore High Court."
          }
        ]
      },
      {
        "heading": "Frequently Asked Questions About Family Court in Lahore?",
        "subheading": "Practical Questions and Answers",
        "description": "Common questions from clients considering family court action or needing specialist representation.",
        "blocks": [
          {
            "type": "paragraph",
            "text": "**Where exactly is the court complex?** Aiwan-e-Adal, Mall Road, Lahore. The complex houses the Senior Civil Judges (Family), Civil Judges (Family), and Guardian Court. It is near the Mall and accessible by public transport. Our office is in DHA Phase 3, a short drive away."
          },
          {
            "type": "paragraph",
            "text": "**How long does khula take?** Uncontested khula under the Dissolution of Muslim Marriages Act 1939 typically takes 6 to 9 months. The reconciliation stage is quick if there is no contest. Once the judge is satisfied that the woman's grounds are valid and she is consenting, the decree is issued."
          },
          {
            "type": "paragraph",
            "text": "**Can I consult before filing suit?** Yes. We offer initial consultations to advise on your case, applicable law, realistic timelines, and costs. We listen without judgment and tell you what we can do. No obligation follows consultation."
          },
          {
            "type": "paragraph",
            "text": "**Do you represent overseas Pakistanis?** Yes. We represent overseas Pakistanis in family cases in Lahore. Remote consultations via Zoom and WhatsApp are available. Court appearances are made by us in person."
          },
          {
            "type": "paragraph",
            "text": "**What does legal representation cost?** Fees vary by case type and complexity. Uncontested khula or talaq suits are usually fixed-fee. Contested cases are charged stage-by-stage: pleading, evidence, and argument. We provide a written fee estimate after the initial consultation. No hidden costs."
          },
          {
            "type": "paragraph",
            "text": "**How do I book a consultation?** Contact us via the form on this site, call +92-319-4959420, or WhatsApp the same number. We respond within one business day and schedule a consultation at your convenience. Consultations can be in-person at our Lahore office or remote."
          }
        ]
      }
    ]
  }
}